odoo/addons/web_environment_ribbon/README.rst
odoo/addons/web_environment_ribbon/__init__.py
odoo/addons/web_environment_ribbon/__manifest__.py
odoo/addons/web_environment_ribbon/data/ribbon_data.xml
odoo/addons/web_environment_ribbon/i18n/de.po
odoo/addons/web_environment_ribbon/i18n/fr.po
odoo/addons/web_environment_ribbon/i18n/hr.po
odoo/addons/web_environment_ribbon/i18n/nl_NL.po
odoo/addons/web_environment_ribbon/i18n/pt_BR.po
odoo/addons/web_environment_ribbon/i18n/sl.po
odoo/addons/web_environment_ribbon/models/__init__.py
odoo/addons/web_environment_ribbon/models/web_environment_ribbon_backend.py
odoo/addons/web_environment_ribbon/static/description/icon.png
odoo/addons/web_environment_ribbon/static/description/screenshot.png
odoo/addons/web_environment_ribbon/static/src/css/ribbon.css
odoo/addons/web_environment_ribbon/static/src/js/ribbon.js
odoo/addons/web_environment_ribbon/view/base_view.xml
odoo11_addon_web_environment_ribbon-11.0.1.0.2.dist-info/DESCRIPTION.rst
odoo11_addon_web_environment_ribbon-11.0.1.0.2.dist-info/METADATA
odoo11_addon_web_environment_ribbon-11.0.1.0.2.dist-info/RECORD
odoo11_addon_web_environment_ribbon-11.0.1.0.2.dist-info/WHEEL
odoo11_addon_web_environment_ribbon-11.0.1.0.2.dist-info/metadata.json
odoo11_addon_web_environment_ribbon-11.0.1.0.2.dist-info/top_level.txt
